{
  "first": 3,
  "second": 1,
  "third": 0,
  "style": 2,
  "win_points" : 20,
  "players": [
    {
      "name": "Mark",
      "first": 2,
      "second": 2,
      "third": 3,
      "style": 0,
      "leagues" : 3,
      "starts" : true
    },
    {
      "name": "Russ",
      "first": 4,
      "second": 2,
      "third": 1,
      "style": 2,
      "leagues" : 1,
      "starts" : false
    },
    {
      "name": "Riley",
      "first": 1,
      "second": 3,
      "third": 3,
      "style": 0,
      "leagues" : 0,
      "starts" : false
    }
  ]
}